LICENSE.md
README.md
flask_cognito.py
setup.py
Flask_Cognito.egg-info/PKG-INFO
Flask_Cognito.egg-info/SOURCES.txt
Flask_Cognito.egg-info/dependency_links.txt
Flask_Cognito.egg-info/not-zip-safe
Flask_Cognito.egg-info/requires.txt
Flask_Cognito.egg-info/top_level.txt