Metadata-Version: 2.1
Name: Flask-Cognito
Version: 1.19
Summary: Authenticate users to Cognito user pool via JWT.
Home-page: https://github.com/jetbridge/flask_cognito
Author: Mischa Spiegelmock
Author-email: mischa@mvstg.biz
License: MIT
Keywords: flask aws cognito jwt authentication auth serverless
Platform: any
Classifier: Environment :: Web Environment
Classifier: Intended Audience :: Developers
Classifier: License :: OSI Approved :: BSD License
Classifier: Operating System :: OS Independent
Classifier: Programming Language :: Python
Classifier: Topic :: Internet :: WWW/HTTP :: Dynamic Content
Classifier: Topic :: Software Development :: Libraries :: Python Modules
License-File: LICENSE.md
Requires-Dist: Flask
Requires-Dist: cognitojwt>=1.1.0
Requires-Dist: werkzeug
Requires-Dist: requests
